scikit_vector_fields-1.0.2.dist-info/licenses/LICENSE
skvf/__init__.py
skvf/data.py
skvf/entities.py
skvf/operations.py
skvf/plot.py
scikit_vector_fields-1.0.2.dist-info/METADATA
scikit_vector_fields-1.0.2.dist-info/WHEEL
scikit_vector_fields-1.0.2.dist-info/top_level.txt
scikit_vector_fields-1.0.2.dist-info/RECORD
