Metadata-Version: 2.4
Name: scikit-vector-fields
Version: 1.0.2
Summary: A package to perform vector field computations
Author-email: Sarang Pendharker <sarang@ece.iitkgp.ac.in>
Project-URL: Homepage, https://github.com/sarang-IITKgp/scikit-vector-fields
Project-URL: Bug Tracker, https://github.com/sarang-IITKgp/scikit-vector-fields/issues
Classifier: Programming Language :: Python :: 3
Classifier: License :: OSI Approved :: BSD License
Classifier: Operating System :: OS Independent
Classifier: Development Status :: 4 - Beta
Classifier: Topic :: Scientific/Engineering
Requires-Python: >=3.7
License-File: LICENSE
Requires-Dist: numpy
Requires-Dist: matplotlib
Requires-Dist: mayavi
Requires-Dist: PyQt5
Requires-Dist: pandas
Requires-Dist: regex
Dynamic: license-file
